net/__init__.py
net/api.py
net/environment.py
net/imports.py
net/connections/__init__.py
net/connections/connect.py
net/connections/event.py
net/connections/flag.py
net/connections/subscribe.py
net/defaults/__init__.py
net/defaults/flags.py
net/defaults/handlers.py
net/peer/__init__.py
net/peer/handler.py
net/peer/peer.py
net/peer/server.py
app_net-0.6.2.dist-info/LICENSE
app_net-0.6.2.dist-info/METADATA
app_net-0.6.2.dist-info/WHEEL
app_net-0.6.2.dist-info/entry_points.txt
app_net-0.6.2.dist-info/top_level.txt
app_net-0.6.2.dist-info/RECORD
