Metadata-Version: 2.1
Name: app-net
Version: 0.6.2
Summary: Python program communication interface
Home-page: https://github.com/aldmbmtl/net
Author: Alex Hatfield
Author-email: alex@hatfieldfx.com
License: MIT license
Keywords: app-net
Platform: UNKNOWN
Classifier: Development Status :: 2 - Pre-Alpha
Classifier: Intended Audience :: Developers
Classifier: License :: OSI Approved :: MIT License
Classifier: Natural Language :: English
Classifier: Programming Language :: Python :: 2
Classifier: Programming Language :: Python :: 2.7
Classifier: Programming Language :: Python :: 3
Classifier: Programming Language :: Python :: 3.4
Classifier: Programming Language :: Python :: 3.5
Classifier: Programming Language :: Python :: 3.6
Classifier: Programming Language :: Python :: 3.7
Requires-Dist: six
